cloudgenix_vff_push_config/__init__.py
cloudgenix_vff_push_config-1.1.0.dist-info/METADATA
cloudgenix_vff_push_config-1.1.0.dist-info/RECORD
cloudgenix_vff_push_config-1.1.0.dist-info/WHEEL
cloudgenix_vff_push_config-1.1.0.dist-info/entry_points.txt
cloudgenix_vff_push_config-1.1.0.dist-info/top_level.txt
