Metadata-Version: 2.1
Name: cloudgenix-vff-push-config
Version: 1.1.0
Summary: Virtual Form Factor Config Push for CloudGenix
Home-page: https://github.com/ebob9/vff_push_config
Author: Aaron Edwards
Author-email: cloudgenix_vff_push_config@ebob9.com
License: MIT
Platform: UNKNOWN
Classifier: Development Status :: 5 - Production/Stable
Classifier: Intended Audience :: Developers
Classifier: License :: OSI Approved :: MIT License
Classifier: Programming Language :: Python :: 2.7
Classifier: Programming Language :: Python :: 3
Requires-Dist: pyserial (>=3.0)
Requires-Dist: pexpect (>=4.0)
